ntnx_clustermgmt_py_client/__init__.py
ntnx_clustermgmt_py_client/api_client.py
ntnx_clustermgmt_py_client/api_response.py
ntnx_clustermgmt_py_client/configuration.py
ntnx_clustermgmt_py_client/custom_retry.py
ntnx_clustermgmt_py_client/rest.py
ntnx_clustermgmt_py_client/api/__init__.py
ntnx_clustermgmt_py_client/api/bmc_api.py
ntnx_clustermgmt_py_client/api/cluster_profiles_api.py
ntnx_clustermgmt_py_client/api/clusters_api.py
ntnx_clustermgmt_py_client/api/cvms_api.py
ntnx_clustermgmt_py_client/api/disks_api.py
ntnx_clustermgmt_py_client/api/password_manager_api.py
ntnx_clustermgmt_py_client/api/pcie_devices_api.py
ntnx_clustermgmt_py_client/api/ssl_certificate_api.py
ntnx_clustermgmt_py_client/api/storage_containers_api.py
ntnx_clustermgmt_py_client/api/vcenter_extensions_api.py
ntnx_clustermgmt_py_client/models/__init__.py
ntnx_clustermgmt_py_client/models/OneOfclustermgmt/__init__.py
ntnx_clustermgmt_py_client/models/OneOfclustermgmt/v4/__init__.py
ntnx_clustermgmt_py_client/models/OneOfclustermgmt/v4/ahv/__init__.py
ntnx_clustermgmt_py_client/models/OneOfclustermgmt/v4/ahv/config/ListPcieDevicesApiResponsedata.py
ntnx_clustermgmt_py_client/models/OneOfclustermgmt/v4/ahv/config/__init__.py
ntnx_clustermgmt_py_client/models/OneOfclustermgmt/v4/config/AddDiskApiResponsedata.py
ntnx_clustermgmt_py_client/models/OneOfclustermgmt/v4/config/AddSnmpTransportsApiResponsedata.py
ntnx_clustermgmt_py_client/models/OneOfclustermgmt/v4/config/ApplyClusterProfileApiResponsedata.py
ntnx_clustermgmt_py_client/models/OneOfclustermgmt/v4/config/AssociateCategoriesToClusterApiResponsedata.py
ntnx_clustermgmt_py_client/models/OneOfclustermgmt/v4/config/ChangeSystemUserPasswordApiResponsedata.py
ntnx_clustermgmt_py_client/models/OneOfclustermgmt/v4/config/CheckHypervisorRequirementsApiResponsedata.py
ntnx_clustermgmt_py_client/models/OneOfclustermgmt/v4/config/ClearThickProvisionedSpaceApiResponsedata.py
ntnx_clustermgmt_py_client-4.2.1.dist-info/LICENSE.txt
ntnx_clustermgmt_py_client-4.2.1.dist-info/METADATA
ntnx_clustermgmt_py_client-4.2.1.dist-info/WHEEL
ntnx_clustermgmt_py_client-4.2.1.dist-info/top_level.txt
ntnx_clustermgmt_py_client-4.2.1.dist-info/RECORD
